ExamenZika/Examen.py
ExamenZika/__init__.py
ZikaUF4-0.0.1.dist-info/METADATA
ZikaUF4-0.0.1.dist-info/WHEEL
ZikaUF4-0.0.1.dist-info/top_level.txt
ZikaUF4-0.0.1.dist-info/RECORD
