Metadata-Version: 2.1
Name: ZikaUF4
Version: 0.0.1
Summary: Un programa para leer y realizar Pruebas(Examenes)
Home-page: UNKNOWN
Author: Zikaria Muhammad Parveen
Author-email: Zikaria.muhammadparveen@gmail.com
License: MIT
Platform: UNKNOWN
Classifier: Programming Language :: Python :: 3
Classifier: License :: OSI Approved :: MIT License
Classifier: Operating System :: OS Independent
Requires-Dist: pickle
